gntplib/__init__.py
gntplib/__version__.py
gntplib/async.py
gntplib/async_gntp.py
gntplib/ciphers.py
gntplib/compat.py
gntplib/connections.py
gntplib/constants.py
gntplib/exceptions.py
gntplib/image_validator.py
gntplib/keys.py
gntplib/lib.py
gntplib/models.py
gntplib/notifier.py
gntplib/packers.py
gntplib/requests.py
gntplib/utils.py
gntplib-3.0.9.dist-info/licenses/LICENSE
gntplib-3.0.9.dist-info/METADATA
gntplib-3.0.9.dist-info/WHEEL
gntplib-3.0.9.dist-info/top_level.txt
gntplib-3.0.9.dist-info/RECORD
