Metadata-Version: 2.4
Name: gntplib
Version: 3.0.9
Summary: A Growl Notification Transport Protocol (GNTP), client library for Python 3.
Home-page: http://github.com/cumulus13/gntplib
Author: Hadi Cahyadi
Author-email: cumulus13@gmail.com
Maintainer: cumulus13
Maintainer-email: cumulus13@gmail.com
License: MIT
Keywords: gntp growl async notification advanced
Platform: any
Classifier: Development Status :: 3 - Alpha
Classifier: Intended Audience :: Developers
Classifier: Operating System :: OS Independent
Classifier: Programming Language :: Python
Classifier: Programming Language :: Python :: 3
Classifier: Topic :: Software Development :: Libraries :: Python Modules
License-File: LICENSE
Provides-Extra: extra
Requires-Dist: tornado; extra == "extra"
Provides-Extra: async
Requires-Dist: tornado; extra == "async"
Provides-Extra: ciphers
Requires-Dist: pycryptodome; extra == "ciphers"
Provides-Extra: all
Requires-Dist: tornado; extra == "all"
Requires-Dist: pycryptodome; extra == "all"
Dynamic: author
Dynamic: author-email
Dynamic: classifier
Dynamic: description
Dynamic: description-content-type
Dynamic: home-page
Dynamic: keywords
Dynamic: license
Dynamic: license-file
Dynamic: maintainer
Dynamic: maintainer-email
Dynamic: platform
Dynamic: provides-extra
Dynamic: summary
